[{"model": 0, "score_sum": 24.357582430820912, "score_min": 0.006445066072046757, "score_max": 0.41694021224975586, "score_mean": 0.03747320373972448, "count": 650, "adj_cnt": 0, "snt_pos_cnt": 192, "snt_neg_cnt": 326, "rsv_sum": 3575, "rsv_min": 1, "rsv_max": 10, "rsv_mean": 5.5, "adj_prop": 0.0}, {"model": 1, "score_sum": 20.010098602622747, "score_min": 0.00907861441373825, "score_max": 0.22761960327625275, "score_mean": 0.030784767080958075, "count": 650, "adj_cnt": 0, "snt_pos_cnt": 129, "snt_neg_cnt": 270, "rsv_sum": 3575, "rsv_min": 1, "rsv_max": 10, "rsv_mean": 5.5, "adj_prop": 0.0}, {"model": 2, "score_sum": 37.75820936751552, "score_min": 0.0011503052664920688, "score_max": 0.8222547173500061, "score_mean": 0.058089552873100796, "count": 650, "adj_cnt": 0, "snt_pos_cnt": 93, "snt_neg_cnt": 312, "rsv_sum": 3575, "rsv_min": 1, "rsv_max": 10, "rsv_mean": 5.5, "adj_prop": 0.0}, {"model": 3, "score_sum": 31.008591745980084, "score_min": 0.010478680953383446, "score_max": 0.5140720009803772, "score_mean": 0.047705525763046285, "count": 650, "adj_cnt": 0, "snt_pos_cnt": 134, "snt_neg_cnt": 264, "rsv_sum": 3575, "rsv_min": 1, "rsv_max": 10, "rsv_mean": 5.5, "adj_prop": 0.0}, {"model": 4, "score_sum": 25.65959860710427, "score_min": 0.0027989079244434834, "score_max": 0.7026469111442566, "score_mean": 0.03947630554939119, "count": 650, "adj_cnt": 0, "snt_pos_cnt": 121, "snt_neg_cnt": 266, "rsv_sum": 3575, "rsv_min": 1, "rsv_max": 10, "rsv_mean": 5.5, "adj_prop": 0.0}, {"model": 5, "score_sum": 16.665140851400793, "score_min": 0.007467853836715221, "score_max": 0.27243638038635254, "score_mean": 0.025638678232924296, "count": 650, "adj_cnt": 0, "snt_pos_cnt": 172, "snt_neg_cnt": 191, "rsv_sum": 3575, "rsv_min": 1, "rsv_max": 10, "rsv_mean": 5.5, "adj_prop": 0.0}, {"model": 6, "score_sum": 18.324736484326422, "score_min": 0.006612085737287998, "score_max": 0.21991240978240967, "score_mean": 0.02819190228357911, "count": 650, "adj_cnt": 0, "snt_pos_cnt": 165, "snt_neg_cnt": 206, "rsv_sum": 3575, "rsv_min": 1, "rsv_max": 10, "rsv_mean": 5.5, "adj_prop": 0.0}, {"model": 7, "score_sum": 23.24065407505259, "score_min": 0.005702418275177479, "score_max": 0.509896457195282, "score_mean": 0.03575485242315783, "count": 650, "adj_cnt": 0, "snt_pos_cnt": 66, "snt_neg_cnt": 221, "rsv_sum": 3575, "rsv_min": 1, "rsv_max": 10, "rsv_mean": 5.5, "adj_prop": 0.0}, {"model": 8, "score_sum": 16.64692969014868, "score_min": 0.0032382486388087273, "score_max": 0.3615163564682007, "score_mean": 0.025610661061767202, "count": 650, "adj_cnt": 0, "snt_pos_cnt": 171, "snt_neg_cnt": 161, "rsv_sum": 3575, "rsv_min": 1, "rsv_max": 10, "rsv_mean": 5.5, "adj_prop": 0.0}, {"model": 9, "score_sum": 23.571342586074024, "score_min": 0.0032505688723176718, "score_max": 0.6900802850723267, "score_mean": 0.03626360397857542, "count": 650, "adj_cnt": 0, "snt_pos_cnt": 80, "snt_neg_cnt": 246, "rsv_sum": 3575, "rsv_min": 1, "rsv_max": 10, "rsv_mean": 5.5, "adj_prop": 0.0}, {"model": 10, "score_sum": 21.207977803424, "score_min": 0.005786949303001165, "score_max": 0.4314032196998596, "score_mean": 0.032627658159113844, "count": 650, "adj_cnt": 0, "snt_pos_cnt": 58, "snt_neg_cnt": 283, "rsv_sum": 3575, "rsv_min": 1, "rsv_max": 10, "rsv_mean": 5.5, "adj_prop": 0.0}, {"model": 11, "score_sum": 20.21557840402238, "score_min": 0.002222759649157524, "score_max": 0.5771418213844299, "score_mean": 0.031100889852342124, "count": 650, "adj_cnt": 0, "snt_pos_cnt": 146, "snt_neg_cnt": 185, "rsv_sum": 3575, "rsv_min": 1, "rsv_max": 10, "rsv_mean": 5.5, "adj_prop": 0.0}, {"model": 12, "score_sum": 18.42061443347484, "score_min": 0.005830769892781973, "score_max": 0.19404368102550507, "score_mean": 0.028339406820730523, "count": 650, "adj_cnt": 0, "snt_pos_cnt": 169, "snt_neg_cnt": 208, "rsv_sum": 3575, "rsv_min": 1, "rsv_max": 10, "rsv_mean": 5.5, "adj_prop": 0.0}, {"model": 13, "score_sum": 15.68820180837065, "score_min": 0.0039155371487140656, "score_max": 0.3974619507789612, "score_mean": 0.024135695089801, "count": 650, "adj_cnt": 0, "snt_pos_cnt": 103, "snt_neg_cnt": 246, "rsv_sum": 3575, "rsv_min": 1, "rsv_max": 10, "rsv_mean": 5.5, "adj_prop": 0.0}, {"model": 14, "score_sum": 24.998746033292264, "score_min": 0.004925007000565529, "score_max": 0.5490525364875793, "score_mean": 0.0384596092819881, "count": 650, "adj_cnt": 0, "snt_pos_cnt": 71, "snt_neg_cnt": 204, "rsv_sum": 3575, "rsv_min": 1, "rsv_max": 10, "rsv_mean": 5.5, "adj_prop": 0.0}, {"model": 15, "score_sum": 25.764468758832663, "score_min": 0.004408813547343016, "score_max": 0.5794598460197449, "score_mean": 0.03963764424435794, "count": 650, "adj_cnt": 0, "snt_pos_cnt": 69, "snt_neg_cnt": 208, "rsv_sum": 3575, "rsv_min": 1, "rsv_max": 10, "rsv_mean": 5.5, "adj_prop": 0.0}, {"model": 16, "score_sum": 42.60669408086687, "score_min": 0.003298915456980467, "score_max": 0.5602404475212097, "score_mean": 0.06554876012441058, "count": 650, "adj_cnt": 0, "snt_pos_cnt": 48, "snt_neg_cnt": 236, "rsv_sum": 3575, "rsv_min": 1, "rsv_max": 10, "rsv_mean": 5.5, "adj_prop": 0.0}, {"model": 17, "score_sum": 33.95805291598663, "score_min": 0.0008019474917091429, "score_max": 0.9356012940406799, "score_mean": 0.05224315833228712, "count": 650, "adj_cnt": 0, "snt_pos_cnt": 128, "snt_neg_cnt": 242, "rsv_sum": 3575, "rsv_min": 1, "rsv_max": 10, "rsv_mean": 5.5, "adj_prop": 0.0}, {"model": 18, "score_sum": 42.61373611073941, "score_min": 0.003298915456980467, "score_max": 0.5602404475212097, "score_mean": 0.06555959401652217, "count": 650, "adj_cnt": 0, "snt_pos_cnt": 48, "snt_neg_cnt": 235, "rsv_sum": 3575, "rsv_min": 1, "rsv_max": 10, "rsv_mean": 5.5, "adj_prop": 0.0}]