[{"model": 0, "category": "Invisible Negative", "score_sum": 7.5799761693924665, "score_min": 0.008834969252347946, "score_max": 0.31645187735557556, "score_mean": 0.03847703639285516, "count": 197, "adj_cnt": 0, "snt_pos_cnt": 3, "snt_neg_cnt": 188, "snt_neu_cnt": 6, "rsv_sum": 1101, "rsv_min": 1, "rsv_max": 10, "rsv_mean": 5.588832487309645, "score_prop": 31.119575150451425, "rsv_prop": 30.797202797202797, "score_prop_overall": 31.119575150451425, "rsv_prop_overall": 30.797202797202797, "adj_prop": 0.0}, {"model": 0, "category": "Invisible Positive", "score_sum": 5.677084338851273, "score_min": 0.010191311128437519, "score_max": 0.41694021224975586, "score_mean": 0.04236630103620353, "count": 134, "adj_cnt": 0, "snt_pos_cnt": 110, "snt_neg_cnt": 6, "snt_neu_cnt": 18, "rsv_sum": 855, "rsv_min": 1, "rsv_max": 10, "rsv_mean": 6.380597014925373, "score_prop": 23.307257011138198, "rsv_prop": 23.916083916083917, "score_prop_overall": 23.307257011138198, "rsv_prop_overall": 23.916083916083917, "adj_prop": 0.0}, {"model": 0, "category": "Visible Positive", "score_sum": 0.6267618583515286, "score_min": 0.012506258673965931, "score_max": 0.3260170519351959, "score_mean": 0.08953740833593267, "count": 7, "adj_cnt": 0, "snt_pos_cnt": 7, "snt_neg_cnt": 0, "snt_neu_cnt": 0, "rsv_sum": 37, "rsv_min": 1, "rsv_max": 10, "rsv_mean": 5.285714285714286, "score_prop": 2.573169402717301, "rsv_prop": 1.034965034965035, "score_prop_overall": 2.573169402717301, "rsv_prop_overall": 1.034965034965035, "adj_prop": 0.0}, {"model": 0, "category": "unknown", "score_sum": 10.473760064225644, "score_min": 0.006445066072046757, "score_max": 0.34051892161369324, "score_mean": 0.03356974379559501, "count": 312, "adj_cnt": 0, "snt_pos_cnt": 72, "snt_neg_cnt": 132, "snt_neu_cnt": 108, "rsv_sum": 1582, "rsv_min": 1, "rsv_max": 10, "rsv_mean": 5.07051282051282, "score_prop": 42.99999843569308, "rsv_prop": 44.25174825174825, "score_prop_overall": 42.99999843569308, "rsv_prop_overall": 44.25174825174825, "adj_prop": 0.0}, {"model": 1, "category": "Invisible Negative", "score_sum": 2.901991382241249, "score_min": 0.009748736396431923, "score_max": 0.1048324853181839, "score_mean": 0.030229076898346346, "count": 96, "adj_cnt": 0, "snt_pos_cnt": 0, "snt_neg_cnt": 96, "snt_neu_cnt": 0, "rsv_sum": 501, "rsv_min": 1, "rsv_max": 10, "rsv_mean": 5.21875, "score_prop": 14.502634094271187, "rsv_prop": 14.013986013986013, "score_prop_overall": 14.502634094271187, "rsv_prop_overall": 14.013986013986013, "adj_prop": 0.0}, {"model": 1, "category": "Invisible Positive", "score_sum": 3.0598510801792145, "score_min": 0.00907861441373825, "score_max": 0.11788859218358994, "score_mean": 0.028072028258524902, "count": 109, "adj_cnt": 0, "snt_pos_cnt": 77, "snt_neg_cnt": 10, "snt_neu_cnt": 22, "rsv_sum": 572, "rsv_min": 1, "rsv_max": 10, "rsv_mean": 5.247706422018348, "score_prop": 15.291534244504703, "rsv_prop": 16.0, "score_prop_overall": 15.291534244504703, "rsv_prop_overall": 16.0, "adj_prop": 0.0}, {"model": 1, "category": "Visible Positive", "score_sum": 0.5939620323479176, "score_min": 0.013872567564249039, "score_max": 0.16657975316047668, "score_mean": 0.03712262702174485, "count": 16, "adj_cnt": 0, "snt_pos_cnt": 16, "snt_neg_cnt": 0, "snt_neu_cnt": 0, "rsv_sum": 108, "rsv_min": 1, "rsv_max": 10, "rsv_mean": 6.75, "score_prop": 2.9683113718893233, "rsv_prop": 3.020979020979021, "score_prop_overall": 2.9683113718893233, "rsv_prop_overall": 3.020979020979021, "adj_prop": 0.0}, {"model": 1, "category": "unknown", "score_sum": 13.454294107854366, "score_min": 0.009326953440904617, "score_max": 0.22761960327625275, "score_mean": 0.031361990927399455, "count": 429, "adj_cnt": 0, "snt_pos_cnt": 36, "snt_neg_cnt": 164, "snt_neu_cnt": 229, "rsv_sum": 2394, "rsv_min": 1, "rsv_max": 10, "rsv_mean": 5.580419580419581, "score_prop": 67.23752028933478, "rsv_prop": 66.96503496503496, "score_prop_overall": 67.23752028933478, "rsv_prop_overall": 66.96503496503496, "adj_prop": 0.0}, {"model": 2, "category": "Invisible Negative", "score_sum": 2.3340871579712257, "score_min": 0.0011503052664920688, "score_max": 0.13053986430168152, "score_mean": 0.035909033199557315, "count": 65, "adj_cnt": 0, "snt_pos_cnt": 0, "snt_neg_cnt": 53, "snt_neu_cnt": 12, "rsv_sum": 338, "rsv_min": 1, "rsv_max": 10, "rsv_mean": 5.2, "score_prop": 6.181668032116238, "rsv_prop": 9.454545454545455, "score_prop_overall": 6.181668032116238, "rsv_prop_overall": 9.454545454545455, "adj_prop": 0.0}, {"model": 2, "category": "Invisible Positive", "score_sum": 3.4907983453013003, "score_min": 0.007130330894142389, "score_max": 0.5531386137008667, "score_mean": 0.06713073740964039, "count": 52, "adj_cnt": 0, "snt_pos_cnt": 41, "snt_neg_cnt": 10, "snt_neu_cnt": 1, "rsv_sum": 332, "rsv_min": 1, "rsv_max": 10, "rsv_mean": 6.384615384615385, "score_prop": 9.245137425146371, "rsv_prop": 9.286713286713287, "score_prop_overall": 9.245137425146371, "rsv_prop_overall": 9.286713286713287, "adj_prop": 0.0}, {"model": 2, "category": "Visible Negative", "score_sum": 0.2289236569777131, "score_min": 0.014563129283487797, "score_max": 0.14092929661273956, "score_mean": 0.04578473139554262, "count": 5, "adj_cnt": 0, "snt_pos_cnt": 0, "snt_neg_cnt": 5, "snt_neu_cnt": 0, "rsv_sum": 16, "rsv_min": 1, "rsv_max": 9, "rsv_mean": 3.2, "score_prop": 0.6062884358458555, "rsv_prop": 0.44755244755244755, "score_prop_overall": 0.6062884358458555, "rsv_prop_overall": 0.44755244755244755, "adj_prop": 0.0}, {"model": 2, "category": "Visible Positive", "score_sum": 0.6262064725160599, "score_min": 0.012155674397945404, "score_max": 0.1519058644771576, "score_mean": 0.03683567485388588, "count": 17, "adj_cnt": 0, "snt_pos_cnt": 5, "snt_neg_cnt": 0, "snt_neu_cnt": 12, "rsv_sum": 71, "rsv_min": 1, "rsv_max": 10, "rsv_mean": 4.176470588235294, "score_prop": 1.658464431988672, "rsv_prop": 1.986013986013986, "score_prop_overall": 1.658464431988672, "rsv_prop_overall": 1.986013986013986, "adj_prop": 0.0}, {"model": 2, "category": "unknown", "score_sum": 31.07819373474922, "score_min": 0.001150617958046496, "score_max": 0.8222547173500061, "score_mean": 0.060818383042562076, "count": 511, "adj_cnt": 0, "snt_pos_cnt": 47, "snt_neg_cnt": 244, "snt_neu_cnt": 220, "rsv_sum": 2818, "rsv_min": 1, "rsv_max": 10, "rsv_mean": 5.514677103718199, "score_prop": 82.30844167490287, "rsv_prop": 78.82517482517483, "score_prop_overall": 82.30844167490287, "rsv_prop_overall": 78.82517482517483, "adj_prop": 0.0}, {"model": 3, "category": "Invisible Negative", "score_sum": 5.105811767280102, "score_min": 0.012523517943918705, "score_max": 0.184076189994812, "score_mean": 0.04558760506500091, "count": 112, "adj_cnt": 0, "snt_pos_cnt": 0, "snt_neg_cnt": 112, "snt_neu_cnt": 0, "rsv_sum": 589, "rsv_min": 1, "rsv_max": 10, "rsv_mean": 5.258928571428571, "score_prop": 16.465796992996346, "rsv_prop": 16.475524475524477, "score_prop_overall": 16.465796992996346, "rsv_prop_overall": 16.475524475524477, "adj_prop": 0.0}, {"model": 3, "category": "Invisible Positive", "score_sum": 4.4191640093922615, "score_min": 0.010655081830918789, "score_max": 0.5140720009803772, "score_mean": 0.059718432559354884, "count": 74, "adj_cnt": 0, "snt_pos_cnt": 63, "snt_neg_cnt": 0, "snt_neu_cnt": 11, "rsv_sum": 405, "rsv_min": 1, "rsv_max": 10, "rsv_mean": 5.472972972972973, "score_prop": 14.25141794762465, "rsv_prop": 11.328671328671328, "score_prop_overall": 14.25141794762465, "rsv_prop_overall": 11.328671328671328, "adj_prop": 0.0}, {"model": 3, "category": "Visible Negative", "score_sum": 0.10497020743787289, "score_min": 0.019488608464598656, "score_max": 0.08548159897327423, "score_mean": 0.05248510371893644, "count": 2, "adj_cnt": 0, "snt_pos_cnt": 0, "snt_neg_cnt": 0, "snt_neu_cnt": 2, "rsv_sum": 11, "rsv_min": 2, "rsv_max": 9, "rsv_mean": 5.5, "score_prop": 0.3385197505832592, "rsv_prop": 0.3076923076923077, "score_prop_overall": 0.3385197505832592, "rsv_prop_overall": 0.3076923076923077, "adj_prop": 0.0}, {"model": 3, "category": "Visible Positive", "score_sum": 0.5490037314593792, "score_min": 0.016492465510964394, "score_max": 0.04101339727640152, "score_mean": 0.02745018657296896, "count": 20, "adj_cnt": 0, "snt_pos_cnt": 17, "snt_neg_cnt": 0, "snt_neu_cnt": 3, "rsv_sum": 62, "rsv_min": 1, "rsv_max": 6, "rsv_mean": 3.1, "score_prop": 1.7704890823703767, "rsv_prop": 1.7342657342657342, "score_prop_overall": 1.7704890823703767, "rsv_prop_overall": 1.7342657342657342, "adj_prop": 0.0}, {"model": 3, "category": "unknown", "score_sum": 20.82964203041047, "score_min": 0.010478680953383446, "score_max": 0.33212050795555115, "score_mean": 0.047125886946630016, "count": 442, "adj_cnt": 0, "snt_pos_cnt": 54, "snt_neg_cnt": 152, "snt_neu_cnt": 236, "rsv_sum": 2508, "rsv_min": 1, "rsv_max": 10, "rsv_mean": 5.67420814479638, "score_prop": 67.17377622642537, "rsv_prop": 70.15384615384616, "score_prop_overall": 67.17377622642537, "rsv_prop_overall": 70.15384615384616, "adj_prop": 0.0}, {"model": 4, "category": "Invisible Negative", "score_sum": 3.081684049218893, "score_min": 0.009448807686567307, "score_max": 0.12172707170248032, "score_mean": 0.03112812170928175, "count": 99, "adj_cnt": 0, "snt_pos_cnt": 0, "snt_neg_cnt": 99, "snt_neu_cnt": 0, "rsv_sum": 540, "rsv_min": 1, "rsv_max": 10, "rsv_mean": 5.454545454545454, "score_prop": 12.009868495626737, "rsv_prop": 15.104895104895105, "score_prop_overall": 12.009868495626737, "rsv_prop_overall": 15.104895104895105, "adj_prop": 0.0}, {"model": 4, "category": "Invisible Positive", "score_sum": 3.374588591977954, "score_min": 0.009785722941160202, "score_max": 0.19717158377170563, "score_mean": 0.04622724098599937, "count": 73, "adj_cnt": 0, "snt_pos_cnt": 59, "snt_neg_cnt": 0, "snt_neu_cnt": 14, "rsv_sum": 433, "rsv_min": 1, "rsv_max": 10, "rsv_mean": 5.931506849315069, "score_prop": 13.151369371162513, "rsv_prop": 12.111888111888112, "score_prop_overall": 13.151369371162513, "rsv_prop_overall": 12.111888111888112, "adj_prop": 0.0}, {"model": 4, "category": "Visible Negative", "score_sum": 0.6488774064928293, "score_min": 0.01411905512213707, "score_max": 0.06428010016679764, "score_mean": 0.036048744805157185, "count": 18, "adj_cnt": 0, "snt_pos_cnt": 0, "snt_neg_cnt": 1, "snt_neu_cnt": 17, "rsv_sum": 100, "rsv_min": 1, "rsv_max": 10, "rsv_mean": 5.555555555555555, "score_prop": 2.5287901670962896, "rsv_prop": 2.797202797202797, "score_prop_overall": 2.5287901670962896, "rsv_prop_overall": 2.797202797202797, "adj_prop": 0.0}, {"model": 4, "category": "Visible Positive", "score_sum": 1.372171862050891, "score_min": 0.016794495284557343, "score_max": 0.10294623672962189, "score_mean": 0.04731627110520314, "count": 29, "adj_cnt": 0, "snt_pos_cnt": 24, "snt_neg_cnt": 0, "snt_neu_cnt": 5, "rsv_sum": 183, "rsv_min": 1, "rsv_max": 10, "rsv_mean": 6.310344827586207, "score_prop": 5.347596753407449, "rsv_prop": 5.118881118881119, "score_prop_overall": 5.347596753407449, "rsv_prop_overall": 5.118881118881119, "adj_prop": 0.0}, {"model": 4, "category": "unknown", "score_sum": 17.182276697363704, "score_min": 0.0027989079244434834, "score_max": 0.7026469111442566, "score_mean": 0.039866071223581684, "count": 431, "adj_cnt": 0, "snt_pos_cnt": 38, "snt_neg_cnt": 166, "snt_neu_cnt": 227, "rsv_sum": 2319, "rsv_min": 1, "rsv_max": 10, "rsv_mean": 5.380510440835267, "score_prop": 66.96237521270702, "rsv_prop": 64.86713286713287, "score_prop_overall": 66.96237521270702, "rsv_prop_overall": 64.86713286713287, "adj_prop": 0.0}, {"model": 5, "category": "Invisible Negative", "score_sum": 0.604440301656723, "score_min": 0.008607937954366207, "score_max": 0.029327237978577614, "score_mean": 0.0172697229044778, "count": 35, "adj_cnt": 0, "snt_pos_cnt": 0, "snt_neg_cnt": 35, "snt_neu_cnt": 0, "rsv_sum": 139, "rsv_min": 1, "rsv_max": 9, "rsv_mean": 3.9714285714285715, "score_prop": 3.626973855464994, "rsv_prop": 3.888111888111888, "score_prop_overall": 3.626973855464994, "rsv_prop_overall": 3.888111888111888, "adj_prop": 0.0}, {"model": 5, "category": "Invisible Positive", "score_sum": 3.9713632417842746, "score_min": 0.008771347813308239, "score_max": 0.15850132703781128, "score_mean": 0.027771770921568354, "count": 143, "adj_cnt": 0, "snt_pos_cnt": 125, "snt_neg_cnt": 0, "snt_neu_cnt": 18, "rsv_sum": 869, "rsv_min": 1, "rsv_max": 10, "rsv_mean": 6.076923076923077, "score_prop": 23.830361094430597, "rsv_prop": 24.307692307692307, "score_prop_overall": 23.830361094430597, "rsv_prop_overall": 24.307692307692307, "adj_prop": 0.0}, {"model": 5, "category": "Visible Negative", "score_sum": 0.7849384006112814, "score_min": 0.018139634281396866, "score_max": 0.08928339928388596, "score_mean": 0.03924692003056407, "count": 20, "adj_cnt": 0, "snt_pos_cnt": 0, "snt_neg_cnt": 1, "snt_neu_cnt": 19, "rsv_sum": 129, "rsv_min": 1, "rsv_max": 10, "rsv_mean": 6.45, "score_prop": 4.710061604701668, "rsv_prop": 3.6083916083916083, "score_prop_overall": 4.710061604701668, "rsv_prop_overall": 3.6083916083916083, "adj_prop": 0.0}, {"model": 5, "category": "Visible Positive", "score_sum": 0.2667798539623618, "score_min": 0.013707411475479603, "score_max": 0.037859492003917694, "score_mean": 0.022231654496863484, "count": 12, "adj_cnt": 0, "snt_pos_cnt": 10, "snt_neg_cnt": 0, "snt_neu_cnt": 2, "rsv_sum": 46, "rsv_min": 1, "rsv_max": 7, "rsv_mean": 3.8333333333333335, "score_prop": 1.6008256776295866, "rsv_prop": 1.2867132867132867, "score_prop_overall": 1.6008256776295866, "rsv_prop_overall": 1.2867132867132867, "adj_prop": 0.0}, {"model": 5, "category": "unknown", "score_sum": 11.037619053386152, "score_min": 0.007467853836715221, "score_max": 0.27243638038635254, "score_mean": 0.02508549784860489, "count": 440, "adj_cnt": 0, "snt_pos_cnt": 37, "snt_neg_cnt": 155, "snt_neu_cnt": 248, "rsv_sum": 2392, "rsv_min": 1, "rsv_max": 10, "rsv_mean": 5.4363636363636365, "score_prop": 66.23177776777315, "rsv_prop": 66.9090909090909, "score_prop_overall": 66.23177776777315, "rsv_prop_overall": 66.9090909090909, "adj_prop": 0.0}, {"model": 6, "category": "Invisible Negative", "score_sum": 0.6198766967281699, "score_min": 0.007970952428877354, "score_max": 0.03473668918013573, "score_mean": 0.017218797131338053, "count": 36, "adj_cnt": 0, "snt_pos_cnt": 0, "snt_neg_cnt": 34, "snt_neu_cnt": 2, "rsv_sum": 147, "rsv_min": 1, "rsv_max": 9, "rsv_mean": 4.083333333333333, "score_prop": 3.3827318458760103, "rsv_prop": 4.111888111888112, "score_prop_overall": 3.3827318458760103, "rsv_prop_overall": 4.111888111888112, "adj_prop": 0.0}, {"model": 6, "category": "Invisible Positive", "score_sum": 0.7663133796304464, "score_min": 0.008404121734201908, "score_max": 0.07334452122449875, "score_mean": 0.03331797302741071, "count": 23, "adj_cnt": 0, "snt_pos_cnt": 23, "snt_neg_cnt": 0, "snt_neu_cnt": 0, "rsv_sum": 159, "rsv_min": 1, "rsv_max": 10, "rsv_mean": 6.913043478260869, "score_prop": 4.18185211168462, "rsv_prop": 4.4475524475524475, "score_prop_overall": 4.18185211168462, "rsv_prop_overall": 4.4475524475524475, "adj_prop": 0.0}, {"model": 6, "category": "Visible Negative", "score_sum": 0.07091257441788912, "score_min": 0.014064340852200985, "score_max": 0.022526275366544724, "score_mean": 0.01772814360447228, "count": 4, "adj_cnt": 0, "snt_pos_cnt": 0, "snt_neg_cnt": 0, "snt_neu_cnt": 4, "rsv_sum": 10, "rsv_min": 1, "rsv_max": 4, "rsv_mean": 2.5, "score_prop": 0.38697732149404884, "rsv_prop": 0.27972027972027974, "score_prop_overall": 0.38697732149404884, "rsv_prop_overall": 0.27972027972027974, "adj_prop": 0.0}, {"model": 6, "category": "Visible Positive", "score_sum": 4.647206107154489, "score_min": 0.006612085737287998, "score_max": 0.19199499487876892, "score_mean": 0.04647206107154488, "count": 100, "adj_cnt": 0, "snt_pos_cnt": 52, "snt_neg_cnt": 12, "snt_neu_cnt": 36, "rsv_sum": 607, "rsv_min": 1, "rsv_max": 10, "rsv_mean": 6.07, "score_prop": 25.360288870343936, "rsv_prop": 16.97902097902098, "score_prop_overall": 25.360288870343936, "rsv_prop_overall": 16.97902097902098, "adj_prop": 0.0}, {"model": 6, "category": "unknown", "score_sum": 12.220427726395428, "score_min": 0.0069382633082568645, "score_max": 0.21991240978240967, "score_mean": 0.02509328075235201, "count": 487, "adj_cnt": 0, "snt_pos_cnt": 90, "snt_neg_cnt": 160, "snt_neu_cnt": 237, "rsv_sum": 2652, "rsv_min": 1, "rsv_max": 10, "rsv_mean": 5.44558521560575, "score_prop": 66.68814985060138, "rsv_prop": 74.18181818181819, "score_prop_overall": 66.68814985060138, "rsv_prop_overall": 74.18181818181819, "adj_prop": 0.0}, {"model": 7, "category": "Invisible Negative", "score_sum": 0.03192003443837166, "score_min": 0.010503137484192848, "score_max": 0.02141689695417881, "score_mean": 0.01596001721918583, "count": 2, "adj_cnt": 0, "snt_pos_cnt": 0, "snt_neg_cnt": 2, "snt_neu_cnt": 0, "rsv_sum": 9, "rsv_min": 2, "rsv_max": 7, "rsv_mean": 4.5, "score_prop": 0.1373456802691102, "rsv_prop": 0.2517482517482518, "score_prop_overall": 0.1373456802691102, "rsv_prop_overall": 0.2517482517482518, "adj_prop": 0.0}, {"model": 7, "category": "Invisible Positive", "score_sum": 1.479037987999618, "score_min": 0.01508531253784895, "score_max": 0.22949722409248352, "score_mean": 0.05688607646152377, "count": 26, "adj_cnt": 0, "snt_pos_cnt": 24, "snt_neg_cnt": 0, "snt_neu_cnt": 2, "rsv_sum": 142, "rsv_min": 1, "rsv_max": 10, "rsv_mean": 5.461538461538462, "score_prop": 6.364011887201033, "rsv_prop": 3.972027972027972, "score_prop_overall": 6.364011887201033, "rsv_prop_overall": 3.972027972027972, "adj_prop": 0.0}, {"model": 7, "category": "Visible Negative", "score_sum": 0.7838681442663074, "score_min": 0.008244093507528305, "score_max": 0.06407048553228378, "score_mean": 0.027029936009183013, "count": 29, "adj_cnt": 0, "snt_pos_cnt": 0, "snt_neg_cnt": 1, "snt_neu_cnt": 28, "rsv_sum": 160, "rsv_min": 1, "rsv_max": 9, "rsv_mean": 5.517241379310345, "score_prop": 3.3728316842327666, "rsv_prop": 4.475524475524476, "score_prop_overall": 3.3728316842327666, "rsv_prop_overall": 4.475524475524476, "adj_prop": 0.0}, {"model": 7, "category": "Visible Positive", "score_sum": 0.5475020157173276, "score_min": 0.011991574428975582, "score_max": 0.0848608911037445, "score_mean": 0.030416778650962643, "count": 18, "adj_cnt": 0, "snt_pos_cnt": 16, "snt_neg_cnt": 0, "snt_neu_cnt": 2, "rsv_sum": 93, "rsv_min": 1, "rsv_max": 9, "rsv_mean": 5.166666666666667, "score_prop": 2.355794350491354, "rsv_prop": 2.6013986013986012, "score_prop_overall": 2.355794350491354, "rsv_prop_overall": 2.6013986013986012, "adj_prop": 0.0}, {"model": 7, "category": "unknown", "score_sum": 20.398325892630965, "score_min": 0.005702418275177479, "score_max": 0.509896457195282, "score_mean": 0.03547534937848863, "count": 575, "adj_cnt": 0, "snt_pos_cnt": 26, "snt_neg_cnt": 218, "snt_neu_cnt": 331, "rsv_sum": 3171, "rsv_min": 1, "rsv_max": 10, "rsv_mean": 5.514782608695652, "score_prop": 87.77001639780573, "rsv_prop": 88.6993006993007, "score_prop_overall": 87.77001639780573, "rsv_prop_overall": 88.6993006993007, "adj_prop": 0.0}, {"model": 8, "category": "Invisible Negative", "score_sum": 0.45935761695727706, "score_min": 0.004327893722802401, "score_max": 0.04057535529136658, "score_mean": 0.013510518145802267, "count": 34, "adj_cnt": 0, "snt_pos_cnt": 0, "snt_neg_cnt": 34, "snt_neu_cnt": 0, "rsv_sum": 141, "rsv_min": 1, "rsv_max": 9, "rsv_mean": 4.147058823529412, "score_prop": 2.7594134504521617, "rsv_prop": 3.944055944055944, "score_prop_overall": 2.7594134504521617, "rsv_prop_overall": 3.944055944055944, "adj_prop": 0.0}, {"model": 8, "category": "Invisible Positive", "score_sum": 0.9075733334757388, "score_min": 0.004594452679157257, "score_max": 0.13232038915157318, "score_mean": 0.018907777780744556, "count": 48, "adj_cnt": 0, "snt_pos_cnt": 45, "snt_neg_cnt": 0, "snt_neu_cnt": 3, "rsv_sum": 290, "rsv_min": 1, "rsv_max": 10, "rsv_mean": 6.041666666666667, "score_prop": 5.451896237735793, "rsv_prop": 8.111888111888112, "score_prop_overall": 5.451896237735793, "rsv_prop_overall": 8.111888111888112, "adj_prop": 0.0}, {"model": 8, "category": "Visible Negative", "score_sum": 1.0997255137190223, "score_min": 0.00822391826659441, "score_max": 0.14170876145362854, "score_mean": 0.054986275685951116, "count": 20, "adj_cnt": 0, "snt_pos_cnt": 0, "snt_neg_cnt": 1, "snt_neu_cnt": 19, "rsv_sum": 125, "rsv_min": 1, "rsv_max": 9, "rsv_mean": 6.25, "score_prop": 6.606176239032341, "rsv_prop": 3.4965034965034967, "score_prop_overall": 6.606176239032341, "rsv_prop_overall": 3.4965034965034967, "adj_prop": 0.0}, {"model": 8, "category": "Visible Positive", "score_sum": 3.4355572641361505, "score_min": 0.0032619647681713104, "score_max": 0.23666805028915405, "score_mean": 0.05822978413790086, "count": 59, "adj_cnt": 0, "snt_pos_cnt": 53, "snt_neg_cnt": 3, "snt_neu_cnt": 3, "rsv_sum": 417, "rsv_min": 1, "rsv_max": 10, "rsv_mean": 7.067796610169491, "score_prop": 20.637783231398185, "rsv_prop": 11.664335664335665, "score_prop_overall": 20.637783231398185, "rsv_prop_overall": 11.664335664335665, "adj_prop": 0.0}, {"model": 8, "category": "unknown", "score_sum": 10.744715961860493, "score_min": 0.0032382486388087273, "score_max": 0.3615163564682007, "score_mean": 0.02197283427783332, "count": 489, "adj_cnt": 0, "snt_pos_cnt": 73, "snt_neg_cnt": 123, "snt_neu_cnt": 293, "rsv_sum": 2602, "rsv_min": 1, "rsv_max": 10, "rsv_mean": 5.321063394683026, "score_prop": 64.54473084138152, "rsv_prop": 72.78321678321679, "score_prop_overall": 64.54473084138152, "rsv_prop_overall": 72.78321678321679, "adj_prop": 0.0}, {"model": 9, "category": "Invisible Negative", "score_sum": 0.7754703504033387, "score_min": 0.006146858911961317, "score_max": 0.04384089633822441, "score_mean": 0.018913910985447285, "count": 41, "adj_cnt": 0, "snt_pos_cnt": 3, "snt_neg_cnt": 38, "snt_neu_cnt": 0, "rsv_sum": 168, "rsv_min": 1, "rsv_max": 10, "rsv_mean": 4.097560975609756, "score_prop": 3.289886214888275, "rsv_prop": 4.699300699300699, "score_prop_overall": 3.289886214888275, "rsv_prop_overall": 4.699300699300699, "adj_prop": 0.0}, {"model": 9, "category": "Invisible Positive", "score_sum": 0.8853872655890882, "score_min": 0.007398488000035286, "score_max": 0.05678915977478027, "score_mean": 0.021080649180692575, "count": 42, "adj_cnt": 0, "snt_pos_cnt": 23, "snt_neg_cnt": 19, "snt_neu_cnt": 0, "rsv_sum": 209, "rsv_min": 1, "rsv_max": 10, "rsv_mean": 4.976190476190476, "score_prop": 3.7562021015815024, "rsv_prop": 5.846153846153846, "score_prop_overall": 3.7562021015815024, "rsv_prop_overall": 5.846153846153846, "adj_prop": 0.0}, {"model": 9, "category": "Visible Negative", "score_sum": 0.19511879421770573, "score_min": 0.01070847176015377, "score_max": 0.03562140092253685, "score_mean": 0.01773807220160961, "count": 11, "adj_cnt": 0, "snt_pos_cnt": 0, "snt_neg_cnt": 1, "snt_neu_cnt": 10, "rsv_sum": 32, "rsv_min": 1, "rsv_max": 7, "rsv_mean": 2.909090909090909, "score_prop": 0.8277797223692389, "rsv_prop": 0.8951048951048951, "score_prop_overall": 0.8277797223692389, "rsv_prop_overall": 0.8951048951048951, "adj_prop": 0.0}, {"model": 9, "category": "Visible Positive", "score_sum": 2.858394625596702, "score_min": 0.009689036756753922, "score_max": 0.1907406598329544, "score_mean": 0.06496351421810687, "count": 44, "adj_cnt": 0, "snt_pos_cnt": 33, "snt_neg_cnt": 3, "snt_neu_cnt": 8, "rsv_sum": 294, "rsv_min": 1, "rsv_max": 10, "rsv_mean": 6.681818181818182, "score_prop": 12.126566890107672, "rsv_prop": 8.223776223776223, "score_prop_overall": 12.126566890107672, "rsv_prop_overall": 8.223776223776223, "adj_prop": 0.0}, {"model": 9, "category": "unknown", "score_sum": 18.85697155026719, "score_min": 0.0032505688723176718, "score_max": 0.6900802850723267, "score_mean": 0.036830022559115605, "count": 512, "adj_cnt": 0, "snt_pos_cnt": 21, "snt_neg_cnt": 185, "snt_neu_cnt": 306, "rsv_sum": 2872, "rsv_min": 1, "rsv_max": 10, "rsv_mean": 5.609375, "score_prop": 79.99956507105331, "rsv_prop": 80.33566433566433, "score_prop_overall": 79.99956507105331, "rsv_prop_overall": 80.33566433566433, "adj_prop": 0.0}, {"model": 10, "category": "Invisible Negative", "score_sum": 0.508634002879262, "score_min": 0.009276612661778927, "score_max": 0.059212736785411835, "score_mean": 0.019562846264587, "count": 26, "adj_cnt": 0, "snt_pos_cnt": 0, "snt_neg_cnt": 26, "snt_neu_cnt": 0, "rsv_sum": 106, "rsv_min": 1, "rsv_max": 9, "rsv_mean": 4.076923076923077, "score_prop": 2.398314481436055, "rsv_prop": 2.965034965034965, "score_prop_overall": 2.398314481436055, "rsv_prop_overall": 2.965034965034965, "adj_prop": 0.0}, {"model": 10, "category": "Invisible Positive", "score_sum": 0.8667534780688584, "score_min": 0.00749526871368289, "score_max": 0.12469429522752762, "score_mean": 0.027959789615124464, "count": 31, "adj_cnt": 0, "snt_pos_cnt": 20, "snt_neg_cnt": 8, "snt_neu_cnt": 3, "rsv_sum": 173, "rsv_min": 1, "rsv_max": 10, "rsv_mean": 5.580645161290323, "score_prop": 4.086921846593607, "rsv_prop": 4.839160839160839, "score_prop_overall": 4.086921846593607, "rsv_prop_overall": 4.839160839160839, "adj_prop": 0.0}, {"model": 10, "category": "Visible Negative", "score_sum": 0.38181205093860626, "score_min": 0.008679094724357128, "score_max": 0.0512179359793663, "score_mean": 0.025454136729240417, "count": 15, "adj_cnt": 0, "snt_pos_cnt": 0, "snt_neg_cnt": 15, "snt_neu_cnt": 0, "rsv_sum": 64, "rsv_min": 1, "rsv_max": 10, "rsv_mean": 4.266666666666667, "score_prop": 1.800322758150771, "rsv_prop": 1.7902097902097902, "score_prop_overall": 1.800322758150771, "rsv_prop_overall": 1.7902097902097902, "adj_prop": 0.0}, {"model": 10, "category": "Visible Positive", "score_sum": 2.209152737632394, "score_min": 0.013239271938800812, "score_max": 0.4314032196998596, "score_mean": 0.04802505951374769, "count": 46, "adj_cnt": 0, "snt_pos_cnt": 19, "snt_neg_cnt": 0, "snt_neu_cnt": 27, "rsv_sum": 269, "rsv_min": 1, "rsv_max": 10, "rsv_mean": 5.8478260869565215, "score_prop": 10.416611890624145, "rsv_prop": 7.524475524475524, "score_prop_overall": 10.416611890624145, "rsv_prop_overall": 7.524475524475524, "adj_prop": 0.0}, {"model": 10, "category": "unknown", "score_sum": 17.24162553390488, "score_min": 0.005786949303001165, "score_max": 0.32208240032196045, "score_mean": 0.03240907055245278, "count": 532, "adj_cnt": 0, "snt_pos_cnt": 19, "snt_neg_cnt": 234, "snt_neu_cnt": 279, "rsv_sum": 2963, "rsv_min": 1, "rsv_max": 10, "rsv_mean": 5.569548872180451, "score_prop": 81.29782902319542, "rsv_prop": 82.88111888111888, "score_prop_overall": 81.29782902319542, "rsv_prop_overall": 82.88111888111888, "adj_prop": 0.0}, {"model": 11, "category": "Invisible Negative", "score_sum": 0.39888477325439453, "score_min": 0.008729145862162113, "score_max": 0.033388130366802216, "score_mean": 0.022160265180799697, "count": 18, "adj_cnt": 0, "snt_pos_cnt": 0, "snt_neg_cnt": 18, "snt_neu_cnt": 0, "rsv_sum": 76, "rsv_min": 1, "rsv_max": 9, "rsv_mean": 4.222222222222222, "score_prop": 1.9731553818664258, "rsv_prop": 2.125874125874126, "score_prop_overall": 1.9731553818664258, "rsv_prop_overall": 2.125874125874126, "adj_prop": 0.0}, {"model": 11, "category": "Invisible Positive", "score_sum": 1.9207289768382907, "score_min": 0.007547981105744839, "score_max": 0.1674996316432953, "score_mean": 0.027052520800539305, "count": 71, "adj_cnt": 0, "snt_pos_cnt": 58, "snt_neg_cnt": 3, "snt_neu_cnt": 10, "rsv_sum": 454, "rsv_min": 1, "rsv_max": 10, "rsv_mean": 6.394366197183099, "score_prop": 9.50123186411582, "rsv_prop": 12.6993006993007, "score_prop_overall": 9.50123186411582, "rsv_prop_overall": 12.6993006993007, "adj_prop": 0.0}, {"model": 11, "category": "Visible Negative", "score_sum": 0.8090502908453345, "score_min": 0.013017622753977776, "score_max": 0.14788509905338287, "score_mean": 0.03677501322024248, "count": 22, "adj_cnt": 0, "snt_pos_cnt": 0, "snt_neg_cnt": 4, "snt_neu_cnt": 18, "rsv_sum": 119, "rsv_min": 1, "rsv_max": 10, "rsv_mean": 5.409090909090909, "score_prop": 4.002112997589791, "rsv_prop": 3.3286713286713288, "score_prop_overall": 4.002112997589791, "rsv_prop_overall": 3.3286713286713288, "adj_prop": 0.0}, {"model": 11, "category": "Visible Positive", "score_sum": 0.8636452537029982, "score_min": 0.006536952219903469, "score_max": 0.040128953754901886, "score_mean": 0.018774896819630394, "count": 46, "adj_cnt": 0, "snt_pos_cnt": 39, "snt_neg_cnt": 2, "snt_neu_cnt": 5, "rsv_sum": 237, "rsv_min": 1, "rsv_max": 10, "rsv_mean": 5.1521739130434785, "score_prop": 4.272176815535265, "rsv_prop": 6.629370629370629, "score_prop_overall": 4.272176815535265, "rsv_prop_overall": 6.629370629370629, "adj_prop": 0.0}, {"model": 11, "category": "unknown", "score_sum": 16.223269109381363, "score_min": 0.002222759649157524, "score_max": 0.5771418213844299, "score_mean": 0.03290723957278167, "count": 493, "adj_cnt": 0, "snt_pos_cnt": 49, "snt_neg_cnt": 158, "snt_neu_cnt": 286, "rsv_sum": 2689, "rsv_min": 1, "rsv_max": 10, "rsv_mean": 5.454361054766735, "score_prop": 80.25132294089269, "rsv_prop": 75.21678321678321, "score_prop_overall": 80.25132294089269, "rsv_prop_overall": 75.21678321678321, "adj_prop": 0.0}, {"model": 12, "category": "Invisible Negative", "score_sum": 0.5040574884042144, "score_min": 0.008155402727425098, "score_max": 0.04282458499073982, "score_mean": 0.0210023953501756, "count": 24, "adj_cnt": 0, "snt_pos_cnt": 0, "snt_neg_cnt": 22, "snt_neu_cnt": 2, "rsv_sum": 106, "rsv_min": 1, "rsv_max": 9, "rsv_mean": 4.416666666666667, "score_prop": 2.736377172567146, "rsv_prop": 2.965034965034965, "score_prop_overall": 2.736377172567146, "rsv_prop_overall": 2.965034965034965, "adj_prop": 0.0}, {"model": 12, "category": "Invisible Positive", "score_sum": 2.797018852084875, "score_min": 0.009475311264395714, "score_max": 0.10601821541786194, "score_mean": 0.028252715677625002, "count": 99, "adj_cnt": 0, "snt_pos_cnt": 72, "snt_neg_cnt": 0, "snt_neu_cnt": 27, "rsv_sum": 551, "rsv_min": 1, "rsv_max": 10, "rsv_mean": 5.565656565656566, "score_prop": 15.184177825262962, "rsv_prop": 15.412587412587413, "score_prop_overall": 15.184177825262962, "rsv_prop_overall": 15.412587412587413, "adj_prop": 0.0}, {"model": 12, "category": "Visible Negative", "score_sum": 0.4138272050768137, "score_min": 0.019824307411909103, "score_max": 0.04299568012356758, "score_mean": 0.025864200317300856, "count": 16, "adj_cnt": 0, "snt_pos_cnt": 0, "snt_neg_cnt": 2, "snt_neu_cnt": 14, "rsv_sum": 79, "rsv_min": 2, "rsv_max": 8, "rsv_mean": 4.9375, "score_prop": 2.2465439824025997, "rsv_prop": 2.2097902097902096, "score_prop_overall": 2.2465439824025997, "rsv_prop_overall": 2.2097902097902096, "adj_prop": 0.0}, {"model": 12, "category": "Visible Positive", "score_sum": 1.7650100905448198, "score_min": 0.009658217430114746, "score_max": 0.19404368102550507, "score_mean": 0.034608040991074895, "count": 51, "adj_cnt": 0, "snt_pos_cnt": 43, "snt_neg_cnt": 0, "snt_neu_cnt": 8, "rsv_sum": 283, "rsv_min": 1, "rsv_max": 10, "rsv_mean": 5.549019607843137, "score_prop": 9.581711277433598, "rsv_prop": 7.916083916083916, "score_prop_overall": 9.581711277433598, "rsv_prop_overall": 7.916083916083916, "adj_prop": 0.0}, {"model": 12, "category": "unknown", "score_sum": 12.940700797364116, "score_min": 0.005830769892781973, "score_max": 0.14103135466575623, "score_mean": 0.02813195825513938, "count": 460, "adj_cnt": 0, "snt_pos_cnt": 54, "snt_neg_cnt": 184, "snt_neu_cnt": 222, "rsv_sum": 2556, "rsv_min": 1, "rsv_max": 10, "rsv_mean": 5.556521739130435, "score_prop": 70.2511897423337, "rsv_prop": 71.4965034965035, "score_prop_overall": 70.2511897423337, "rsv_prop_overall": 71.4965034965035, "adj_prop": 0.0}, {"model": 13, "category": "Invisible Negative", "score_sum": 0.24833692191168666, "score_min": 0.00565786799415946, "score_max": 0.0268770232796669, "score_mean": 0.015521057619480416, "count": 16, "adj_cnt": 0, "snt_pos_cnt": 0, "snt_neg_cnt": 16, "snt_neu_cnt": 0, "rsv_sum": 74, "rsv_min": 1, "rsv_max": 10, "rsv_mean": 4.625, "score_prop": 1.5829533871701165, "rsv_prop": 2.06993006993007, "score_prop_overall": 1.5829533871701165, "rsv_prop_overall": 2.06993006993007, "adj_prop": 0.0}, {"model": 13, "category": "Invisible Positive", "score_sum": 1.5059997732751071, "score_min": 0.003947394900023937, "score_max": 0.157900869846344, "score_mean": 0.020351348287501448, "count": 74, "adj_cnt": 0, "snt_pos_cnt": 64, "snt_neg_cnt": 0, "snt_neu_cnt": 10, "rsv_sum": 417, "rsv_min": 1, "rsv_max": 10, "rsv_mean": 5.635135135135135, "score_prop": 9.599569100848516, "rsv_prop": 11.664335664335665, "score_prop_overall": 9.599569100848516, "rsv_prop_overall": 11.664335664335665, "adj_prop": 0.0}, {"model": 13, "category": "Visible Negative", "score_sum": 0.7332062446512282, "score_min": 0.005176036152988672, "score_max": 0.08255195617675781, "score_mean": 0.034914583078629914, "count": 21, "adj_cnt": 0, "snt_pos_cnt": 0, "snt_neg_cnt": 20, "snt_neu_cnt": 1, "rsv_sum": 127, "rsv_min": 1, "rsv_max": 10, "rsv_mean": 6.0476190476190474, "score_prop": 4.673615584547211, "rsv_prop": 3.5524475524475525, "score_prop_overall": 4.673615584547211, "rsv_prop_overall": 3.5524475524475525, "adj_prop": 0.0}, {"model": 13, "category": "Visible Positive", "score_sum": 1.1497075483202934, "score_min": 0.0045570735819637775, "score_max": 0.13789474964141846, "score_mean": 0.042581761048899755, "count": 27, "adj_cnt": 0, "snt_pos_cnt": 8, "snt_neg_cnt": 0, "snt_neu_cnt": 19, "rsv_sum": 185, "rsv_min": 1, "rsv_max": 10, "rsv_mean": 6.851851851851852, "score_prop": 7.328485204128695, "rsv_prop": 5.174825174825175, "score_prop_overall": 7.328485204128695, "rsv_prop_overall": 5.174825174825175, "adj_prop": 0.0}, {"model": 13, "category": "unknown", "score_sum": 12.050951320212334, "score_min": 0.0039155371487140656, "score_max": 0.3974619507789612, "score_mean": 0.023537014297289716, "count": 512, "adj_cnt": 0, "snt_pos_cnt": 31, "snt_neg_cnt": 210, "snt_neu_cnt": 271, "rsv_sum": 2772, "rsv_min": 1, "rsv_max": 10, "rsv_mean": 5.4140625, "score_prop": 76.81537672330546, "rsv_prop": 77.53846153846153, "score_prop_overall": 76.81537672330546, "rsv_prop_overall": 77.53846153846153, "adj_prop": 0.0}, {"model": 14, "category": "Invisible Negative", "score_sum": 0.0394694684073329, "score_min": 0.005661356262862682, "score_max": 0.022891227155923843, "score_mean": 0.013156489469110966, "count": 3, "adj_cnt": 0, "snt_pos_cnt": 0, "snt_neg_cnt": 3, "snt_neu_cnt": 0, "rsv_sum": 11, "rsv_min": 2, "rsv_max": 7, "rsv_mean": 3.6666666666666665, "score_prop": 0.15788579297045197, "rsv_prop": 0.3076923076923077, "score_prop_overall": 0.15788579297045197, "rsv_prop_overall": 0.3076923076923077, "adj_prop": 0.0}, {"model": 14, "category": "Invisible Positive", "score_sum": 1.9114829804748297, "score_min": 0.017059864476323128, "score_max": 0.29431673884391785, "score_mean": 0.0707956659435122, "count": 27, "adj_cnt": 0, "snt_pos_cnt": 25, "snt_neg_cnt": 0, "snt_neu_cnt": 2, "rsv_sum": 170, "rsv_min": 2, "rsv_max": 10, "rsv_mean": 6.296296296296297, "score_prop": 7.6463154508998095, "rsv_prop": 4.755244755244755, "score_prop_overall": 7.6463154508998095, "rsv_prop_overall": 4.755244755244755, "adj_prop": 0.0}, {"model": 14, "category": "Visible Negative", "score_sum": 0.9028949569910765, "score_min": 0.0085503114387393, "score_max": 0.07159365713596344, "score_mean": 0.029125643773905693, "count": 31, "adj_cnt": 0, "snt_pos_cnt": 0, "snt_neg_cnt": 1, "snt_neu_cnt": 30, "rsv_sum": 181, "rsv_min": 1, "rsv_max": 9, "rsv_mean": 5.838709677419355, "score_prop": 3.6117609890857705, "rsv_prop": 5.062937062937063, "score_prop_overall": 3.6117609890857705, "rsv_prop_overall": 5.062937062937063, "adj_prop": 0.0}, {"model": 14, "category": "Visible Positive", "score_sum": 0.4819725649431348, "score_min": 0.011711017228662968, "score_max": 0.07619651407003403, "score_mean": 0.028351327349596164, "count": 17, "adj_cnt": 0, "snt_pos_cnt": 15, "snt_neg_cnt": 0, "snt_neu_cnt": 2, "rsv_sum": 76, "rsv_min": 1, "rsv_max": 9, "rsv_mean": 4.470588235294118, "score_prop": 1.9279869650312231, "rsv_prop": 2.125874125874126, "score_prop_overall": 1.9279869650312231, "rsv_prop_overall": 2.125874125874126, "adj_prop": 0.0}, {"model": 14, "category": "unknown", "score_sum": 21.66292606247589, "score_min": 0.004925007000565529, "score_max": 0.5490525364875793, "score_mean": 0.03787224836097183, "count": 572, "adj_cnt": 0, "snt_pos_cnt": 31, "snt_neg_cnt": 200, "snt_neu_cnt": 341, "rsv_sum": 3137, "rsv_min": 1, "rsv_max": 10, "rsv_mean": 5.484265734265734, "score_prop": 86.65605080201274, "rsv_prop": 87.74825174825175, "score_prop_overall": 86.65605080201274, "rsv_prop_overall": 87.74825174825175, "adj_prop": 0.0}, {"model": 15, "category": "Invisible Negative", "score_sum": 0.026767112780362368, "score_min": 0.005483305547386408, "score_max": 0.02128380723297596, "score_mean": 0.013383556390181184, "count": 2, "adj_cnt": 0, "snt_pos_cnt": 0, "snt_neg_cnt": 2, "snt_neu_cnt": 0, "rsv_sum": 8, "rsv_min": 1, "rsv_max": 7, "rsv_mean": 4.0, "score_prop": 0.10389157653866228, "rsv_prop": 0.22377622377622378, "score_prop_overall": 0.10389157653866228, "rsv_prop_overall": 0.22377622377622378, "adj_prop": 0.0}, {"model": 15, "category": "Invisible Positive", "score_sum": 1.4283390482887626, "score_min": 0.012327522039413452, "score_max": 0.2227010726928711, "score_mean": 0.0571335619315505, "count": 25, "adj_cnt": 0, "snt_pos_cnt": 23, "snt_neg_cnt": 0, "snt_neu_cnt": 2, "rsv_sum": 135, "rsv_min": 1, "rsv_max": 10, "rsv_mean": 5.4, "score_prop": 5.543832716516208, "rsv_prop": 3.7762237762237763, "score_prop_overall": 5.543832716516208, "rsv_prop_overall": 3.7762237762237763, "adj_prop": 0.0}, {"model": 15, "category": "Visible Negative", "score_sum": 1.067999648861587, "score_min": 0.010335715487599373, "score_max": 0.08493861556053162, "score_mean": 0.03445160157618023, "count": 31, "adj_cnt": 0, "snt_pos_cnt": 0, "snt_neg_cnt": 1, "snt_neu_cnt": 30, "rsv_sum": 204, "rsv_min": 2, "rsv_max": 9, "rsv_mean": 6.580645161290323, "score_prop": 4.145242267009491, "rsv_prop": 5.706293706293707, "score_prop_overall": 4.145242267009491, "rsv_prop_overall": 5.706293706293707, "adj_prop": 0.0}, {"model": 15, "category": "Visible Positive", "score_sum": 0.4654285404831171, "score_min": 0.01125000324100256, "score_max": 0.08098533749580383, "score_mean": 0.02908928378019482, "count": 16, "adj_cnt": 0, "snt_pos_cnt": 14, "snt_neg_cnt": 0, "snt_neu_cnt": 2, "rsv_sum": 72, "rsv_min": 1, "rsv_max": 9, "rsv_mean": 4.5, "score_prop": 1.8064744312787637, "rsv_prop": 2.013986013986014, "score_prop_overall": 1.8064744312787637, "rsv_prop_overall": 2.013986013986014, "adj_prop": 0.0}, {"model": 15, "category": "unknown", "score_sum": 22.775934408418834, "score_min": 0.004408813547343016, "score_max": 0.5794598460197449, "score_mean": 0.03954155279239381, "count": 576, "adj_cnt": 0, "snt_pos_cnt": 32, "snt_neg_cnt": 205, "snt_neu_cnt": 339, "rsv_sum": 3156, "rsv_min": 1, "rsv_max": 10, "rsv_mean": 5.479166666666667, "score_prop": 88.40055900865687, "rsv_prop": 88.27972027972028, "score_prop_overall": 88.40055900865687, "rsv_prop_overall": 88.27972027972028, "adj_prop": 0.0}, {"model": 16, "category": "Invisible Positive", "score_sum": 1.4699234925210476, "score_min": 0.027438152581453323, "score_max": 0.14572647213935852, "score_mean": 0.07736439434321303, "count": 19, "adj_cnt": 0, "snt_pos_cnt": 19, "snt_neg_cnt": 0, "snt_neu_cnt": 0, "rsv_sum": 122, "rsv_min": 1, "rsv_max": 9, "rsv_mean": 6.421052631578948, "score_prop": 3.4499825068125554, "rsv_prop": 3.4125874125874125, "score_prop_overall": 3.4499825068125554, "rsv_prop_overall": 3.4125874125874125, "adj_prop": 0.0}, {"model": 16, "category": "Visible Positive", "score_sum": 2.276845902670175, "score_min": 0.0035252533853054047, "score_max": 0.11543522030115128, "score_mean": 0.04216381301241064, "count": 54, "adj_cnt": 0, "snt_pos_cnt": 20, "snt_neg_cnt": 0, "snt_neu_cnt": 34, "rsv_sum": 238, "rsv_min": 1, "rsv_max": 9, "rsv_mean": 4.407407407407407, "score_prop": 5.343868966573082, "rsv_prop": 6.6573426573426575, "score_prop_overall": 5.343868966573082, "rsv_prop_overall": 6.6573426573426575, "adj_prop": 0.0}, {"model": 16, "category": "unknown", "score_sum": 38.85992468567565, "score_min": 0.003298915456980467, "score_max": 0.5602404475212097, "score_mean": 0.0673482230254344, "count": 577, "adj_cnt": 0, "snt_pos_cnt": 9, "snt_neg_cnt": 236, "snt_neu_cnt": 332, "rsv_sum": 3215, "rsv_min": 1, "rsv_max": 10, "rsv_mean": 5.571923743500866, "score_prop": 91.20614852661436, "rsv_prop": 89.93006993006993, "score_prop_overall": 91.20614852661436, "rsv_prop_overall": 89.93006993006993, "adj_prop": 0.0}, {"model": 17, "category": "Invisible Negative", "score_sum": 0.14309348165988922, "score_min": 0.004680439829826355, "score_max": 0.0330682173371315, "score_mean": 0.020441925951412747, "count": 7, "adj_cnt": 0, "snt_pos_cnt": 0, "snt_neg_cnt": 7, "snt_neu_cnt": 0, "rsv_sum": 23, "rsv_min": 1, "rsv_max": 6, "rsv_mean": 3.2857142857142856, "score_prop": 0.4213830575442807, "rsv_prop": 0.6433566433566433, "score_prop_overall": 0.4213830575442807, "rsv_prop_overall": 0.6433566433566433, "adj_prop": 0.0}, {"model": 17, "category": "Invisible Positive", "score_sum": 1.0636624447070062, "score_min": 0.006346785929054022, "score_max": 0.1341731995344162, "score_mean": 0.04624619324813071, "count": 23, "adj_cnt": 0, "snt_pos_cnt": 21, "snt_neg_cnt": 0, "snt_neu_cnt": 2, "rsv_sum": 136, "rsv_min": 1, "rsv_max": 10, "rsv_mean": 5.913043478260869, "score_prop": 3.13228337130678, "rsv_prop": 3.804195804195804, "score_prop_overall": 3.13228337130678, "rsv_prop_overall": 3.804195804195804, "adj_prop": 0.0}, {"model": 17, "category": "Visible Negative", "score_sum": 0.5768909414764494, "score_min": 0.0025855808053165674, "score_max": 0.08161947876214981, "score_mean": 0.03036268113033944, "count": 19, "adj_cnt": 0, "snt_pos_cnt": 0, "snt_neg_cnt": 3, "snt_neu_cnt": 16, "rsv_sum": 88, "rsv_min": 1, "rsv_max": 8, "rsv_mean": 4.631578947368421, "score_prop": 1.6988339788023097, "rsv_prop": 2.4615384615384617, "score_prop_overall": 1.6988339788023097, "rsv_prop_overall": 2.4615384615384617, "adj_prop": 0.0}, {"model": 17, "category": "Visible Positive", "score_sum": 2.832509317435324, "score_min": 0.0034704250283539295, "score_max": 0.24885578453540802, "score_mean": 0.05447133302760239, "count": 52, "adj_cnt": 0, "snt_pos_cnt": 27, "snt_neg_cnt": 1, "snt_neu_cnt": 24, "rsv_sum": 349, "rsv_min": 1, "rsv_max": 10, "rsv_mean": 6.711538461538462, "score_prop": 8.341200611363226, "rsv_prop": 9.762237762237762, "score_prop_overall": 8.341200611363226, "rsv_prop_overall": 9.762237762237762, "adj_prop": 0.0}, {"model": 17, "category": "unknown", "score_sum": 29.34189673070796, "score_min": 0.0008019474917091429, "score_max": 0.9356012940406799, "score_mean": 0.05344607783371213, "count": 549, "adj_cnt": 0, "snt_pos_cnt": 80, "snt_neg_cnt": 231, "snt_neu_cnt": 238, "rsv_sum": 2979, "rsv_min": 1, "rsv_max": 10, "rsv_mean": 5.426229508196721, "score_prop": 86.40629898098341, "rsv_prop": 83.32867132867133, "score_prop_overall": 86.40629898098341, "rsv_prop_overall": 83.32867132867133, "adj_prop": 0.0}, {"model": 18, "category": "Invisible Positive", "score_sum": 1.4699235558509827, "score_min": 0.027438152581453323, "score_max": 0.14572647213935852, "score_mean": 0.0773643976763675, "count": 19, "adj_cnt": 0, "snt_pos_cnt": 19, "snt_neg_cnt": 0, "snt_neu_cnt": 0, "rsv_sum": 122, "rsv_min": 1, "rsv_max": 9, "rsv_mean": 6.421052631578948, "score_prop": 3.4494125369132704, "rsv_prop": 3.4125874125874125, "score_prop_overall": 3.4494125369132704, "rsv_prop_overall": 3.4125874125874125, "adj_prop": 0.0}, {"model": 18, "category": "Visible Positive", "score_sum": 2.27853548200801, "score_min": 0.0035252533853054047, "score_max": 0.11543522030115128, "score_mean": 0.04219510151866685, "count": 54, "adj_cnt": 0, "snt_pos_cnt": 20, "snt_neg_cnt": 0, "snt_neu_cnt": 34, "rsv_sum": 239, "rsv_min": 1, "rsv_max": 9, "rsv_mean": 4.425925925925926, "score_prop": 5.3469507486666465, "rsv_prop": 6.685314685314685, "score_prop_overall": 5.3469507486666465, "rsv_prop_overall": 6.685314685314685, "adj_prop": 0.0}, {"model": 18, "category": "unknown", "score_sum": 38.86527707288042, "score_min": 0.003298915456980467, "score_max": 0.5602404475212097, "score_mean": 0.06735749925975809, "count": 577, "adj_cnt": 0, "snt_pos_cnt": 9, "snt_neg_cnt": 235, "snt_neu_cnt": 333, "rsv_sum": 3214, "rsv_min": 1, "rsv_max": 10, "rsv_mean": 5.570190641247834, "score_prop": 91.20363671442009, "rsv_prop": 89.9020979020979, "score_prop_overall": 91.20363671442009, "rsv_prop_overall": 89.9020979020979, "adj_prop": 0.0}]